[
  {
    "audit_id": "4a21f500-46f1-44d8-8a89-68d42fd22152",
    "tenant_id": "default",
    "user_id": "dev-user",
    "action": "tenant_reset",
    "resource_type": "tenant",
    "resource_id": "default",
    "metadata": {
      "removed_files": 17
    },
    "created_at": "2026-05-25 18:38:26.444158+00:00",
    "_id": "6a1497228acf678b68ec9ce9"
  },
  {
    "audit_id": "207f8c95-1630-4856-ab4f-8edc0cb2c6a6",
    "tenant_id": "default",
    "user_id": "dev-user",
    "action": "model_upload",
    "resource_type": "model",
    "resource_id": "6a14975a8acf678b68ec9cea",
    "metadata": {
      "name": "credit_default_underwriting_engine_v1.5",
      "version": "v1"
    },
    "created_at": "2026-05-25 18:39:22.348010+00:00",
    "_id": "6a14975a8acf678b68ec9ceb"
  },
  {
    "audit_id": "31050677-3a92-43a9-913d-1001206803df",
    "tenant_id": "default",
    "user_id": "dev-user",
    "action": "model_delete",
    "resource_type": "model",
    "resource_id": "6a14975a8acf678b68ec9cea",
    "metadata": {
      "name": "credit_default_underwriting_engine_v1.5"
    },
    "created_at": "2026-05-25 18:39:32.506991+00:00",
    "_id": "6a1497648acf678b68ec9cec"
  },
  {
    "audit_id": "31e8fb05-4580-4633-b1f2-a4c0389b4e7c",
    "tenant_id": "default",
    "user_id": "dev-user",
    "action": "model_upload",
    "resource_type": "model",
    "resource_id": "6a1498328acf678b68ec9ced",
    "metadata": {
      "name": "credit_risk_intelligence",
      "version": "v1"
    },
    "created_at": "2026-05-25 18:42:58.085045+00:00",
    "_id": "6a1498328acf678b68ec9cee"
  },
  {
    "audit_id": "3e0cb658-13c2-4831-91c1-b25d228976da",
    "tenant_id": "default",
    "user_id": "dev-user",
    "action": "dataset_upload",
    "resource_type": "dataset",
    "resource_id": "6a14984b8acf678b68ec9cef",
    "metadata": {
      "name": "credit_default_reference_baseline_distribution",
      "version": "v1779734602938"
    },
    "created_at": "2026-05-25 18:43:23.220272+00:00",
    "_id": "6a14984b8acf678b68ec9cf0"
  },
  {
    "audit_id": "08da7501-8b86-4347-a438-fcb4233b545b",
    "tenant_id": "default",
    "user_id": "dev-user",
    "action": "compute_metrics",
    "resource_type": "model",
    "resource_id": "6a1498328acf678b68ec9ced",
    "metadata": {
      "dataset_id": "6a14984b8acf678b68ec9cef"
    },
    "created_at": "2026-05-25 18:43:23.620374+00:00",
    "_id": "6a14984b8acf678b68ec9cf2"
  },
  {
    "audit_id": "57675503-070c-49b0-b6c9-8b6df525683b",
    "tenant_id": "default",
    "user_id": "dev-user",
    "action": "dataset_upload",
    "resource_type": "dataset",
    "resource_id": "6a1498588acf678b68ec9cf3",
    "metadata": {
      "name": "credit_active_economic_recession_shift",
      "version": "v1779734616857"
    },
    "created_at": "2026-05-25 18:43:37.007709+00:00",
    "_id": "6a1498598acf678b68ec9cf4"
  },
  {
    "audit_id": "0e33555b-e09e-4bea-816d-d3888d4ae2b8",
    "tenant_id": "default",
    "user_id": "dev-user",
    "action": "compute_metrics",
    "resource_type": "model",
    "resource_id": "6a1498328acf678b68ec9ced",
    "metadata": {
      "dataset_id": "6a1498588acf678b68ec9cf3"
    },
    "created_at": "2026-05-25 18:43:37.257223+00:00",
    "_id": "6a1498598acf678b68ec9cf6"
  },
  {
    "audit_id": "b466fadf-d624-4e11-900b-ced969f1bb7d",
    "tenant_id": "default",
    "user_id": "dev-user",
    "action": "dataset_upload",
    "resource_type": "dataset",
    "resource_id": "6a1498648acf678b68ec9cf7",
    "metadata": {
      "name": "credit_realtime_risk_predictions_export",
      "version": "v1779734628293"
    },
    "created_at": "2026-05-25 18:43:48.398727+00:00",
    "_id": "6a1498648acf678b68ec9cf8"
  },
  {
    "audit_id": "dc77e244-9c6f-49bb-aaf0-ef9d87b96d94",
    "tenant_id": "default",
    "user_id": "dev-user",
    "action": "compute_metrics",
    "resource_type": "model",
    "resource_id": "6a1498328acf678b68ec9ced",
    "metadata": {
      "dataset_id": "6a1498648acf678b68ec9cf7"
    },
    "created_at": "2026-05-25 18:43:48.829081+00:00",
    "_id": "6a1498648acf678b68ec9cfa"
  },
  {
    "audit_id": "5feb0594-97c4-47a0-952c-b3fe8dd6cda6",
    "tenant_id": "default",
    "user_id": "dev-user",
    "action": "dataset_upload",
    "resource_type": "dataset",
    "resource_id": "6a14986b8acf678b68ec9cfb",
    "metadata": {
      "name": "historical_credit_cardholds_ledger",
      "version": "v1779734635806"
    },
    "created_at": "2026-05-25 18:43:55.946919+00:00",
    "_id": "6a14986b8acf678b68ec9cfc"
  },
  {
    "audit_id": "0702ccb0-f849-410e-86fc-9f7ce981f151",
    "tenant_id": "default",
    "user_id": "dev-user",
    "action": "compute_metrics",
    "resource_type": "model",
    "resource_id": "6a1498328acf678b68ec9ced",
    "metadata": {
      "dataset_id": "6a14986b8acf678b68ec9cfb"
    },
    "created_at": "2026-05-25 18:43:56.191874+00:00",
    "_id": "6a14986c8acf678b68ec9cfe"
  },
  {
    "audit_id": "e504c675-2ade-421f-bdf7-8693b068c0f6",
    "tenant_id": "default",
    "user_id": "dev-user",
    "action": "model_upload",
    "resource_type": "model",
    "resource_id": "6a1498a18acf678b68ec9cff",
    "metadata": {
      "name": "loan_approval_governance",
      "version": "v1"
    },
    "created_at": "2026-05-25 18:44:49.090928+00:00",
    "_id": "6a1498a18acf678b68ec9d00"
  },
  {
    "audit_id": "f86dea6e-6e3e-4e61-a835-377c17baa335",
    "tenant_id": "default",
    "user_id": "dev-user",
    "action": "compute_metrics",
    "resource_type": "model",
    "resource_id": "6a1498a18acf678b68ec9cff",
    "metadata": {
      "dataset_id": "6a14986b8acf678b68ec9cfb"
    },
    "created_at": "2026-05-25 18:44:49.677162+00:00",
    "_id": "6a1498a18acf678b68ec9d02"
  },
  {
    "audit_id": "85f1f2f1-f042-40a2-9569-ccce60113a0a",
    "tenant_id": "default",
    "user_id": "dev-user",
    "action": "dataset_upload",
    "resource_type": "dataset",
    "resource_id": "6a1498aa8acf678b68ec9d03",
    "metadata": {
      "name": "historical_loan_applications_ledger",
      "version": "v1779734697935"
    },
    "created_at": "2026-05-25 18:44:58.042390+00:00",
    "_id": "6a1498aa8acf678b68ec9d04"
  },
  {
    "audit_id": "a6c76d4a-ab49-4298-b6d9-610d1ab12318",
    "tenant_id": "default",
    "user_id": "dev-user",
    "action": "compute_metrics",
    "resource_type": "model",
    "resource_id": "6a1498a18acf678b68ec9cff",
    "metadata": {
      "dataset_id": "6a1498aa8acf678b68ec9d03"
    },
    "created_at": "2026-05-25 18:44:58.364548+00:00",
    "_id": "6a1498aa8acf678b68ec9d06"
  },
  {
    "audit_id": "2ffbaba3-51de-4ed5-b85c-1e02c4a5cedc",
    "tenant_id": "default",
    "user_id": "dev-user",
    "action": "dataset_upload",
    "resource_type": "dataset",
    "resource_id": "6a1498c48acf678b68ec9d07",
    "metadata": {
      "name": "loan_active_production_covariate_shift",
      "version": "v1779734724750"
    },
    "created_at": "2026-05-25 18:45:24.891518+00:00",
    "_id": "6a1498c48acf678b68ec9d08"
  },
  {
    "audit_id": "889ef686-a84c-4513-ad77-73a7dfa3a90c",
    "tenant_id": "default",
    "user_id": "dev-user",
    "action": "compute_metrics",
    "resource_type": "model",
    "resource_id": "6a1498a18acf678b68ec9cff",
    "metadata": {
      "dataset_id": "6a1498c48acf678b68ec9d07"
    },
    "created_at": "2026-05-25 18:45:25.207888+00:00",
    "_id": "6a1498c58acf678b68ec9d0a"
  },
  {
    "audit_id": "d3a0df76-24b5-4ad3-8b81-7b00312bae26",
    "tenant_id": "default",
    "user_id": "dev-user",
    "action": "dataset_upload",
    "resource_type": "dataset",
    "resource_id": "6a1498d18acf678b68ec9d0b",
    "metadata": {
      "name": "loan_baseline_demographic_distribution",
      "version": "v1779734736944"
    },
    "created_at": "2026-05-25 18:45:37.128802+00:00",
    "_id": "6a1498d18acf678b68ec9d0c"
  },
  {
    "audit_id": "2a4aa268-1bf4-4f7b-a3d1-f7c92e604819",
    "tenant_id": "default",
    "user_id": "dev-user",
    "action": "compute_metrics",
    "resource_type": "model",
    "resource_id": "6a1498a18acf678b68ec9cff",
    "metadata": {
      "dataset_id": "6a1498d18acf678b68ec9d0b"
    },
    "created_at": "2026-05-25 18:45:37.400899+00:00",
    "_id": "6a1498d18acf678b68ec9d0e"
  },
  {
    "audit_id": "0dec5086-5f84-4e8b-8e0b-c3d8804a73e0",
    "tenant_id": "default",
    "user_id": "dev-user",
    "action": "dataset_upload",
    "resource_type": "dataset",
    "resource_id": "6a1498d78acf678b68ec9d0f",
    "metadata": {
      "name": "loan_realtime_inference_predictions_export",
      "version": "v1779734743377"
    },
    "created_at": "2026-05-25 18:45:43.539637+00:00",
    "_id": "6a1498d78acf678b68ec9d10"
  },
  {
    "audit_id": "5e0f6af6-17a8-4727-b709-210a895ed653",
    "tenant_id": "default",
    "user_id": "dev-user",
    "action": "compute_metrics",
    "resource_type": "model",
    "resource_id": "6a1498a18acf678b68ec9cff",
    "metadata": {
      "dataset_id": "6a1498d78acf678b68ec9d0f"
    },
    "created_at": "2026-05-25 18:45:43.825061+00:00",
    "_id": "6a1498d78acf678b68ec9d12"
  },
  {
    "audit_id": "12a9cf5e-19e6-4203-92b2-8f1234f3edb1",
    "tenant_id": "default",
    "user_id": "dev-user",
    "action": "model_upload",
    "resource_type": "model",
    "resource_id": "6a1499008acf678b68ec9d13",
    "metadata": {
      "name": "insurance_fraud_detection",
      "version": "v1"
    },
    "created_at": "2026-05-25 18:46:24.589518+00:00",
    "_id": "6a1499008acf678b68ec9d14"
  },
  {
    "audit_id": "ef67b777-f800-42e6-a81e-707e0a42cc1f",
    "tenant_id": "default",
    "user_id": "dev-user",
    "action": "compute_metrics",
    "resource_type": "model",
    "resource_id": "6a1499008acf678b68ec9d13",
    "metadata": {
      "dataset_id": "6a1498d78acf678b68ec9d0f"
    },
    "created_at": "2026-05-25 18:46:25.018416+00:00",
    "_id": "6a1499018acf678b68ec9d16"
  },
  {
    "audit_id": "717b929a-2ae3-4098-8f0c-89943760ca5e",
    "tenant_id": "default",
    "user_id": "dev-user",
    "action": "dataset_upload",
    "resource_type": "dataset",
    "resource_id": "6a14990f8acf678b68ec9d17",
    "metadata": {
      "name": "claims_active_catastrophe_fraud_shift",
      "version": "v1779734799420"
    },
    "created_at": "2026-05-25 18:46:39.540955+00:00",
    "_id": "6a14990f8acf678b68ec9d18"
  },
  {
    "audit_id": "7f685a82-d4d9-4edc-ab5d-bcc179aaffc0",
    "tenant_id": "default",
    "user_id": "dev-user",
    "action": "compute_metrics",
    "resource_type": "model",
    "resource_id": "6a1499008acf678b68ec9d13",
    "metadata": {
      "dataset_id": "6a14990f8acf678b68ec9d17"
    },
    "created_at": "2026-05-25 18:46:39.833207+00:00",
    "_id": "6a14990f8acf678b68ec9d1a"
  },
  {
    "audit_id": "96d96555-7d47-4fdb-9365-5a9b516d5a3f",
    "tenant_id": "default",
    "user_id": "dev-user",
    "action": "dataset_upload",
    "resource_type": "dataset",
    "resource_id": "6a1499128acf678b68ec9d1b",
    "metadata": {
      "name": "claims_fraud_reference_baseline_distribution",
      "version": "v1779734802817"
    },
    "created_at": "2026-05-25 18:46:42.974009+00:00",
    "_id": "6a1499128acf678b68ec9d1c"
  },
  {
    "audit_id": "6429d29c-effd-4a74-a06d-dca9f16ee951",
    "tenant_id": "default",
    "user_id": "dev-user",
    "action": "compute_metrics",
    "resource_type": "model",
    "resource_id": "6a1499008acf678b68ec9d13",
    "metadata": {
      "dataset_id": "6a1499128acf678b68ec9d1b"
    },
    "created_at": "2026-05-25 18:46:43.239197+00:00",
    "_id": "6a1499138acf678b68ec9d1e"
  },
  {
    "audit_id": "82aa17d2-4691-468f-8d37-569a9ee30096",
    "tenant_id": "default",
    "user_id": "dev-user",
    "action": "dataset_upload",
    "resource_type": "dataset",
    "resource_id": "6a1499168acf678b68ec9d1f",
    "metadata": {
      "name": "claims_realtime_fraud_predictions_export",
      "version": "v1779734806429"
    },
    "created_at": "2026-05-25 18:46:46.613675+00:00",
    "_id": "6a1499168acf678b68ec9d20"
  },
  {
    "audit_id": "b82b9d50-e382-4fb0-a65f-909f8b43d950",
    "tenant_id": "default",
    "user_id": "dev-user",
    "action": "compute_metrics",
    "resource_type": "model",
    "resource_id": "6a1499008acf678b68ec9d13",
    "metadata": {
      "dataset_id": "6a1499168acf678b68ec9d1f"
    },
    "created_at": "2026-05-25 18:46:46.911192+00:00",
    "_id": "6a1499168acf678b68ec9d22"
  },
  {
    "audit_id": "08160792-e972-409e-a48a-887dc4a91808",
    "tenant_id": "default",
    "user_id": "dev-user",
    "action": "dataset_upload",
    "resource_type": "dataset",
    "resource_id": "6a14991a8acf678b68ec9d23",
    "metadata": {
      "name": "historical_insurance_claims_ledger",
      "version": "v1779734809923"
    },
    "created_at": "2026-05-25 18:46:50.086890+00:00",
    "_id": "6a14991a8acf678b68ec9d24"
  },
  {
    "audit_id": "33eff52e-789a-4249-994b-5117798de99b",
    "tenant_id": "default",
    "user_id": "dev-user",
    "action": "compute_metrics",
    "resource_type": "model",
    "resource_id": "6a1499008acf678b68ec9d13",
    "metadata": {
      "dataset_id": "6a14991a8acf678b68ec9d23"
    },
    "created_at": "2026-05-25 18:46:50.482007+00:00",
    "_id": "6a14991a8acf678b68ec9d26"
  },
  {
    "audit_id": "c2df2c87-7a10-4fb4-8a7c-e9fc3b91021c",
    "tenant_id": "default",
    "user_id": "dev-user",
    "action": "compute_metrics",
    "resource_type": "model",
    "resource_id": "6a1499008acf678b68ec9d13",
    "metadata": {
      "dataset_id": "6a14991a8acf678b68ec9d23"
    },
    "created_at": "2026-05-25 18:47:13.761641+00:00",
    "_id": "6a1499318acf678b68ec9d28"
  },
  {
    "audit_id": "65565ea7-555a-47d6-a91e-ab1d648ac983",
    "tenant_id": "default",
    "user_id": "dev-user",
    "action": "compute_metrics",
    "resource_type": "model",
    "resource_id": "6a1498a18acf678b68ec9cff",
    "metadata": {
      "dataset_id": "6a1498c48acf678b68ec9d07"
    },
    "created_at": "2026-05-25 18:47:50.851296+00:00",
    "_id": "6a1499568acf678b68ec9d2a"
  },
  {
    "audit_id": "819dfec9-766f-420a-bfc8-f74549f0db86",
    "tenant_id": "default",
    "user_id": "dev-user",
    "action": "dataset_upload",
    "resource_type": "dataset",
    "resource_id": "6a1499888acf678b68ec9d2b",
    "metadata": {
      "name": "claims_active_catastrophe_fraud_shift",
      "version": "v1779734920136"
    },
    "created_at": "2026-05-25 18:48:40.319773+00:00",
    "_id": "6a1499888acf678b68ec9d2c"
  },
  {
    "audit_id": "de2f1f0f-b99e-4953-8345-1ccc6e545b8e",
    "tenant_id": "default",
    "user_id": "dev-user",
    "action": "model_upload",
    "resource_type": "model",
    "resource_id": "6a1499888acf678b68ec9d2d",
    "metadata": {
      "name": "insurance_fraud_detection",
      "version": "v1779734920136"
    },
    "created_at": "2026-05-25 18:48:40.427705+00:00",
    "_id": "6a1499888acf678b68ec9d2e"
  },
  {
    "audit_id": "3ae462ee-1847-4184-a257-a4cbe4bb676a",
    "tenant_id": "default",
    "user_id": "dev-user",
    "action": "compute_metrics",
    "resource_type": "model",
    "resource_id": "6a1499888acf678b68ec9d2d",
    "metadata": {
      "dataset_id": "6a1499888acf678b68ec9d2b"
    },
    "created_at": "2026-05-25 18:48:40.734308+00:00",
    "_id": "6a1499888acf678b68ec9d30"
  },
  {
    "audit_id": "74f60fd2-42e1-4923-829b-8d52d9ba718c",
    "tenant_id": "default",
    "user_id": "dev-user",
    "action": "compute_shap",
    "resource_type": "model",
    "resource_id": "6a1499888acf678b68ec9d2d",
    "metadata": {
      "dataset_id": "6a1499888acf678b68ec9d2b"
    },
    "created_at": "2026-05-25 18:48:49.571741+00:00",
    "_id": "6a1499918acf678b68ec9d32"
  },
  {
    "audit_id": "41f8758e-38cf-4374-ad37-693311d1daad",
    "tenant_id": "default",
    "user_id": "dev-user",
    "action": "governance_analyze",
    "resource_type": "model",
    "resource_id": "6a1499888acf678b68ec9d2d",
    "metadata": {
      "dataset_id": "6a1499888acf678b68ec9d2b"
    },
    "created_at": "2026-05-25 18:48:49.741325+00:00",
    "_id": "6a1499918acf678b68ec9d34"
  },
  {
    "audit_id": "62842e34-e386-4f26-bdfa-2c5cc549d023",
    "tenant_id": "default",
    "user_id": "dev-user",
    "action": "compute_shap",
    "resource_type": "model",
    "resource_id": "6a1498a18acf678b68ec9cff",
    "metadata": {
      "dataset_id": "6a1498c48acf678b68ec9d07"
    },
    "created_at": "2026-05-25 18:49:23.252591+00:00",
    "_id": "6a1499b38acf678b68ec9d36"
  },
  {
    "audit_id": "1fe75ff6-bdff-44d4-a734-33940f4b4e17",
    "tenant_id": "default",
    "user_id": "dev-user",
    "action": "compute_shap",
    "resource_type": "model",
    "resource_id": "6a1498328acf678b68ec9ced",
    "metadata": {
      "dataset_id": "6a1498c48acf678b68ec9d07"
    },
    "created_at": "2026-05-25 18:49:46.300010+00:00",
    "_id": "6a1499ca8acf678b68ec9d38"
  },
  {
    "audit_id": "64c4176f-c3bb-4647-b0f4-2108d9b6b279",
    "tenant_id": "default",
    "user_id": "dev-user",
    "action": "compute_shap",
    "resource_type": "model",
    "resource_id": "6a1498328acf678b68ec9ced",
    "metadata": {
      "dataset_id": "6a14984b8acf678b68ec9cef"
    },
    "created_at": "2026-05-25 18:50:07.050246+00:00",
    "_id": "6a1499df8acf678b68ec9d3a"
  },
  {
    "audit_id": "5d11f72f-1bcd-42ff-be22-6ef2b570ea55",
    "tenant_id": "default",
    "user_id": "dev-user",
    "action": "governance_analyze",
    "resource_type": "model",
    "resource_id": "6a1498328acf678b68ec9ced",
    "metadata": {
      "dataset_id": "6a14984b8acf678b68ec9cef"
    },
    "created_at": "2026-05-25 18:50:21.263081+00:00",
    "_id": "6a1499ed8acf678b68ec9d3c"
  },
  {
    "audit_id": "80ea282a-d8d8-41ed-9d7a-0f4b78e39108",
    "tenant_id": "default",
    "user_id": "dev-user",
    "action": "governance_analyze",
    "resource_type": "model",
    "resource_id": "6a1498328acf678b68ec9ced",
    "metadata": {
      "dataset_id": "6a1499888acf678b68ec9d2b"
    },
    "created_at": "2026-05-25 18:50:28.299489+00:00",
    "_id": "6a1499f48acf678b68ec9d3e"
  },
  {
    "audit_id": "9b1b41a5-15eb-40ef-ada3-b898592bf284",
    "tenant_id": "default",
    "user_id": "dev-user",
    "action": "governance_analyze",
    "resource_type": "model",
    "resource_id": "6a1498328acf678b68ec9ced",
    "metadata": {
      "dataset_id": "6a14991a8acf678b68ec9d23"
    },
    "created_at": "2026-05-25 18:50:38.426946+00:00",
    "_id": "6a1499fe8acf678b68ec9d40"
  },
  {
    "audit_id": "12848f8c-6a6a-4bba-b2a6-139295f46396",
    "tenant_id": "default",
    "user_id": "dev-user",
    "action": "governance_analyze",
    "resource_type": "model",
    "resource_id": "6a1498328acf678b68ec9ced",
    "metadata": {
      "dataset_id": "6a1498588acf678b68ec9cf3"
    },
    "created_at": "2026-05-25 18:50:45.283688+00:00",
    "_id": "6a149a058acf678b68ec9d42"
  },
  {
    "audit_id": "cabda43a-6a28-44b3-bed5-d7ab47a0176f",
    "tenant_id": "default",
    "user_id": "dev-user",
    "action": "governance_analyze",
    "resource_type": "model",
    "resource_id": "6a1498a18acf678b68ec9cff",
    "metadata": {
      "dataset_id": "6a1498588acf678b68ec9cf3"
    },
    "created_at": "2026-05-25 18:50:50.916509+00:00",
    "_id": "6a149a0a8acf678b68ec9d44"
  },
  {
    "audit_id": "e0b65e0c-00a1-485c-a8f2-6f4a0626a0c9",
    "tenant_id": "default",
    "user_id": "dev-user",
    "action": "drift_analyze",
    "resource_type": "dataset",
    "resource_id": "6a14991a8acf678b68ec9d23",
    "metadata": {
      "baseline_dataset_id": "6a1499888acf678b68ec9d2b"
    },
    "created_at": "2026-05-25 18:50:58.563190+00:00",
    "_id": "6a149a128acf678b68ec9d46"
  },
  {
    "audit_id": "c797984f-fe37-4217-a8a1-76cdef6f94e5",
    "tenant_id": "default",
    "user_id": "dev-user",
    "action": "drift_analyze",
    "resource_type": "dataset",
    "resource_id": "6a14984b8acf678b68ec9cef",
    "metadata": {
      "baseline_dataset_id": "6a1498588acf678b68ec9cf3"
    },
    "created_at": "2026-05-25 18:52:29.100871+00:00",
    "_id": "6a149a6d8acf678b68ec9d48"
  },
  {
    "audit_id": "d43c4fe4-0785-4d06-9443-ccf6c6736a3b",
    "tenant_id": "default",
    "user_id": "dev-user",
    "action": "drift_analyze",
    "resource_type": "dataset",
    "resource_id": "6a14991a8acf678b68ec9d23",
    "metadata": {
      "baseline_dataset_id": "6a1498588acf678b68ec9cf3"
    },
    "created_at": "2026-05-25 18:52:40.295261+00:00",
    "_id": "6a149a788acf678b68ec9d4a"
  },
  {
    "audit_id": "f1d528ce-456a-4e1a-a3e1-f901ee63209b",
    "tenant_id": "default",
    "user_id": "dev-user",
    "action": "report_generate_partial",
    "resource_type": "report",
    "resource_id": "6a149a8e8acf678b68ec9d4b",
    "metadata": {
      "model_id": "6a1498a18acf678b68ec9cff",
      "dataset_id": "6a1498588acf678b68ec9cf3"
    },
    "created_at": "2026-05-25 18:53:02.627213+00:00",
    "_id": "6a149a8e8acf678b68ec9d4c"
  },
  {
    "audit_id": "3eaa6f16-1c38-477e-8c7f-9d95bf5d0369",
    "tenant_id": "default",
    "user_id": "dev-user",
    "action": "assistant_chat",
    "resource_type": "assistant_session",
    "resource_id": "6a1498a18acf678b68ec9cff:6a1498d78acf678b68ec9d0f",
    "metadata": {
      "latency_ms": 1008,
      "used_fallback": true
    },
    "created_at": "2026-05-25 18:53:56.785834+00:00",
    "_id": "6a149ac48acf678b68ec9d4e"
  },
  {
    "audit_id": "d3182afa-cead-48fd-8152-019766e7619c",
    "tenant_id": "default",
    "user_id": "dev-user",
    "action": "model_upload",
    "resource_type": "model",
    "resource_id": "6a1545cd37b370b47e1e0763",
    "metadata": {
      "name": "insurance_fraud_detection",
      "version": "v3"
    },
    "created_at": "2026-05-26 07:03:41.631255+00:00",
    "_id": "6a1545cd37b370b47e1e0764"
  },
  {
    "audit_id": "f91da13e-c5b1-459e-90d8-7a27853bd9f6",
    "tenant_id": "default",
    "user_id": "dev-user",
    "action": "compute_metrics",
    "resource_type": "model",
    "resource_id": "6a1545cd37b370b47e1e0763",
    "metadata": {
      "dataset_id": "6a1499888acf678b68ec9d2b"
    },
    "created_at": "2026-05-26 07:03:42.006312+00:00",
    "_id": "6a1545ce37b370b47e1e0766"
  },
  {
    "audit_id": "b479ee6c-5a82-4100-9e6e-f12e52666943",
    "tenant_id": "default",
    "user_id": "dev-user",
    "action": "dataset_upload",
    "resource_type": "dataset",
    "resource_id": "6a1545d737b370b47e1e0767",
    "metadata": {
      "name": "claims_active_catastrophe_fraud_shift",
      "version": "v1779779030977"
    },
    "created_at": "2026-05-26 07:03:51.251134+00:00",
    "_id": "6a1545d737b370b47e1e0768"
  },
  {
    "audit_id": "19a1c518-1630-4fc3-a6cd-a7cef602c5e0",
    "tenant_id": "default",
    "user_id": "dev-user",
    "action": "compute_metrics",
    "resource_type": "model",
    "resource_id": "6a1545cd37b370b47e1e0763",
    "metadata": {
      "dataset_id": "6a1545d737b370b47e1e0767"
    },
    "created_at": "2026-05-26 07:03:51.542854+00:00",
    "_id": "6a1545d737b370b47e1e076a"
  },
  {
    "audit_id": "2912097d-b1ed-4d48-aad5-6610174d54f5",
    "tenant_id": "default",
    "user_id": "dev-user",
    "action": "compute_shap",
    "resource_type": "model",
    "resource_id": "6a1545cd37b370b47e1e0763",
    "metadata": {
      "dataset_id": "6a1545d737b370b47e1e0767"
    },
    "created_at": "2026-05-26 07:04:33.388725+00:00",
    "_id": "6a15460137b370b47e1e076c"
  },
  {
    "audit_id": "a1dc3916-bcc9-4430-acf3-ab698c62692a",
    "tenant_id": "default",
    "user_id": "dev-user",
    "action": "governance_analyze",
    "resource_type": "model",
    "resource_id": "6a1545cd37b370b47e1e0763",
    "metadata": {
      "dataset_id": "6a1545d737b370b47e1e0767"
    },
    "created_at": "2026-05-26 07:06:44.132482+00:00",
    "_id": "6a15468437b370b47e1e076e"
  }
]